pythonxbox/__init__.py
pythonxbox/py.typed
pythonxbox/api/__init__.py
pythonxbox/api/client.py
pythonxbox/api/language.py
pythonxbox/api/provider/__init__.py
pythonxbox/api/provider/baseprovider.py
pythonxbox/api/provider/ratelimitedprovider.py
pythonxbox/api/provider/account/__init__.py
pythonxbox/api/provider/account/models.py
pythonxbox/api/provider/achievements/__init__.py
pythonxbox/api/provider/achievements/models.py
pythonxbox/api/provider/catalog/__init__.py
pythonxbox/api/provider/catalog/const.py
pythonxbox/api/provider/catalog/models.py
pythonxbox/api/provider/cqs/__init__.py
pythonxbox/api/provider/cqs/models.py
pythonxbox/api/provider/gameclips/__init__.py
pythonxbox/api/provider/gameclips/models.py
pythonxbox/api/provider/lists/__init__.py
pythonxbox/api/provider/lists/models.py
pythonxbox/api/provider/mediahub/__init__.py
pythonxbox/api/provider/mediahub/models.py
pythonxbox/api/provider/message/__init__.py
pythonxbox/api/provider/message/models.py
pythonxbox/api/provider/people/__init__.py
pythonxbox/api/provider/people/models.py
pythonxbox/api/provider/presence/__init__.py
pythonxbox/api/provider/presence/models.py
pythonxbox/api/provider/profile/__init__.py
pythonxbox/api/provider/profile/models.py
pythonxbox/api/provider/screenshots/__init__.py
pythonxbox/api/provider/screenshots/models.py
pythonxbox/api/provider/smartglass/__init__.py
pythonxbox/api/provider/smartglass/models.py
pythonxbox/api/provider/titlehub/__init__.py
pythonxbox/api/provider/titlehub/models.py
pythonxbox/api/provider/usersearch/__init__.py
pythonxbox/api/provider/usersearch/models.py
pythonxbox/api/provider/userstats/__init__.py
pythonxbox/api/provider/userstats/models.py
pythonxbox/authentication/__init__.py
pythonxbox/authentication/manager.py
pythonxbox/authentication/models.py
pythonxbox/authentication/xal.py
pythonxbox/common/__init__.py
pythonxbox/common/exceptions.py
pythonxbox/common/filetimes.py
pythonxbox/common/models.py
pythonxbox/common/request_signer.py
python_xbox-0.1.1.dist-info/METADATA
python_xbox-0.1.1.dist-info/WHEEL
python_xbox-0.1.1.dist-info/entry_points.txt
python_xbox-0.1.1.dist-info/licenses/LICENSE
python_xbox-0.1.1.dist-info/RECORD
