Metadata-Version: 2.4
Name: python-xbox
Version: 0.1.1
Summary: A library to authenticate with Xbox Network and use their API
Project-URL: Source, https://github.com/tr4nt0r/python-xbox
Author-email: Manfred Dennerlein Rodelo <manfred@dennerlein.name>
License-Expression: MIT
License-File: LICENSE
Keywords: xbox one live api
Classifier: Development Status :: 5 - Production/Stable
Classifier: Intended Audience :: Developers
Classifier: License :: OSI Approved :: MIT License
Classifier: Operating System :: OS Independent
Classifier: Programming Language :: Python :: 3
Classifier: Programming Language :: Python :: 3.11
Classifier: Programming Language :: Python :: 3.12
Classifier: Programming Language :: Python :: 3.13
Classifier: Programming Language :: Python :: 3.14
Classifier: Topic :: Software Development :: Libraries :: Python Modules
Requires-Python: >=3.11
Requires-Dist: ecdsa>=0.19
Requires-Dist: httpx>=0.25.1
Requires-Dist: ms-cv>=0.1.1
Requires-Dist: pydantic>=2.12
Provides-Extra: cli
Requires-Dist: platformdirs>=4.5.0; extra == 'cli'
